<scoreboard>
<preamble>
<center><h1>AXCIOMA Scoreboard</h1></center>
</preamble>

<group>
  <name>Master on Linux</name>
  <build>
    <name>rhel80_axcioma_release_ndds610rev3</name>
    <url>https://download.remedy.nl/buildlogs/rhel80_axcioma_release_ndds610rev3</url>
    <build_sponsor>Remedy IT</build_sponsor>
    <build_sponsor_url>https://www.remedy.nl</build_sponsor_url>
  </build>
  <build>
    <name>rhel80_axcioma_debug_ndds610rev3</name>
    <url>https://download.remedy.nl/buildlogs/rhel80_axcioma_debug_ndds610rev3</url>
    <build_sponsor>Remedy IT</build_sponsor>
    <build_sponsor_url>https://www.remedy.nl</build_sponsor_url>
  </build>
  <build>
    <name>rhel80_axcioma_valgrind_ndds610rev3</name>
    <url>https://download.remedy.nl/buildlogs/rhel80_axcioma_valgrind_ndds610rev3</url>
    <build_sponsor>Remedy IT</build_sponsor>
    <build_sponsor_url>https://www.remedy.nl</build_sponsor_url>
  </build>
  <build>
    <name>rhel80_axcioma_release_opendds3241</name>
    <url>https://download.remedy.nl/buildlogs/rhel80_axcioma_release_opendds3241</url>
    <build_sponsor>Remedy IT</build_sponsor>
    <build_sponsor_url>https://www.remedy.nl</build_sponsor_url>
  </build>
  <build>
    <name>rhel80_axcioma_debug_opendds3241</name>
    <url>https://download.remedy.nl/buildlogs/rhel80_axcioma_debug_opendds3241</url>
    <build_sponsor>Remedy IT</build_sponsor>
    <build_sponsor_url>https://www.remedy.nl</build_sponsor_url>
  </build>
  <build>
    <name>rhel80_axcioma_master_valgrind_opendds</name>
    <url>https://download.remedy.nl/buildlogs/rhel80_axcioma_master_valgrind_opendds</url>
    <build_sponsor>Remedy IT</build_sponsor>
    <build_sponsor_url>https://www.remedy.nl</build_sponsor_url>
  </build>
  <build>
    <name>rhel80_axcioma_master_opendds</name>
    <url>https://download.remedy.nl/buildlogs/rhel80_axcioma_master_opendds</url>
    <build_sponsor>Remedy IT</build_sponsor>
    <build_sponsor_url>https://www.remedy.nl</build_sponsor_url>
  </build>
  <build>
    <name>rhel80_axcioma_yocto344_zcu102_release_ndds610rev3</name>
    <url>http://download.remedy.nl/buildlogs/rhel80_axcioma_yocto344_zcu102_release_ndds610rev3</url>
    <build_sponsor>Remedy IT</build_sponsor>
    <build_sponsor_url>https://www.remedy.nl</build_sponsor_url>
  </build>
  <build>
    <name>rhel80_axcioma_yocto344_zcu102_debug_ndds610rev3</name>
    <url>http://download.remedy.nl/buildlogs/rhel80_axcioma_yocto344_zcu102_debug_ndds610rev3</url>
    <build_sponsor>Remedy IT</build_sponsor>
    <build_sponsor_url>https://www.remedy.nl</build_sponsor_url>
  </build>
  <build>
    <name>rhel80_axcioma_yocto344_zcu102_debug_opendds3241</name>
    <url>http://download.remedy.nl/buildlogs/rhel80_axcioma_yocto344_zcu102_debug_opendds3241</url>
    <build_sponsor>Remedy IT</build_sponsor>
    <build_sponsor_url>https://www.remedy.nl</build_sponsor_url>
  </build>
  <build>
    <name>rhel80_axcioma_yocto344_zcu102_release_opendds3241</name>
    <url>http://download.remedy.nl/buildlogs/rhel80_axcioma_yocto344_zcu102_release_opendds3241</url>
    <build_sponsor>Remedy IT</build_sponsor>
    <build_sponsor_url>https://www.remedy.nl</build_sponsor_url>
  </build>
</group>

<group>
  <name>v2.3.0 on Linux</name>
  <build>
    <name>rhel80_axcioma230_release_ndds610rev3</name>
    <url>https://download.remedy.nl/buildlogs/axcioma/AXCIOMA_v2.3.0/rhel80_axcioma23x_release_ndds610rev3</url>
    <build_sponsor>Remedy IT</build_sponsor>
    <build_sponsor_url>https://www.remedy.nl</build_sponsor_url>
  </build>
  <build>
    <name>rhel80_axcioma230_debug_ndds610rev3</name>
    <url>https://download.remedy.nl/buildlogs/axcioma/AXCIOMA_v2.3.0/rhel80_axcioma23x_debug_ndds610rev3</url>
    <build_sponsor>Remedy IT</build_sponsor>
    <build_sponsor_url>https://www.remedy.nl</build_sponsor_url>
  </build>
  <build>
    <name>rhel80_axcioma230_valgrind_ndds610rev3</name>
    <url>https://download.remedy.nl/buildlogs/axcioma/AXCIOMA_v2.3.0/rhel80_axcioma23x_valgrind_ndds610rev3</url>
    <build_sponsor>Remedy IT</build_sponsor>
    <build_sponsor_url>https://www.remedy.nl</build_sponsor_url>
  </build>
  <build>
    <name>rhel80_axcioma230_yocto253_zcu102_release_ndds610rev3</name>
    <url>https://download.remedy.nl/buildlogs/axcioma/AXCIOMA_v2.3.0/rhel80_axcioma23x_yocto253_zcu102_release_ndds610rev3</url>
    <build_sponsor>Remedy IT</build_sponsor>
    <build_sponsor_url>https://www.remedy.nl</build_sponsor_url>
  </build>
  <build>
    <name>rhel80_axcioma230_yocto253_zcu102_debug_ndds610rev3</name>
    <url>https://download.remedy.nl/buildlogs/axcioma/AXCIOMA_v2.3.0/rhel80_axcioma23x_yocto253_zcu102_debug_ndds610rev3</url>
    <build_sponsor>Remedy IT</build_sponsor>
    <build_sponsor_url>https://www.remedy.nl</build_sponsor_url>
  </build>
  <build>
    <name>rhel80_axcioma230_release_opendds3220</name>
    <url>https://download.remedy.nl/buildlogs/axcioma/AXCIOMA_v2.3.0/rhel80_axcioma23x_release_opendds3220</url>
    <build_sponsor>Remedy IT</build_sponsor>
    <build_sponsor_url>https://www.remedy.nl</build_sponsor_url>
  </build>
  <build>
    <name>rhel80_axcioma230_debug_opendds3220</name>
    <url>https://download.remedy.nl/buildlogs/axcioma/AXCIOMA_v2.3.0/rhel80_axcioma23x_debug_opendds3220</url>
    <build_sponsor>Remedy IT</build_sponsor>
    <build_sponsor_url>https://www.remedy.nl</build_sponsor_url>
  </build>
  <build>
    <name>rhel80_axcioma230_yocto253_zcu102_release_opendds3220</name>
    <url>https://download.remedy.nl/buildlogs/axcioma/AXCIOMA_v2.3.0/rhel80_axcioma23x_yocto253_zcu102_release_opendds3220</url>
    <build_sponsor>Remedy IT</build_sponsor>
    <build_sponsor_url>https://www.remedy.nl</build_sponsor_url>
  </build>
  <build>
    <name>rhel80_axcioma230_yocto253_zcu102_debug_opendds3220</name>
    <url>https://download.remedy.nl/buildlogs/axcioma/AXCIOMA_v2.3.0/rhel80_axcioma23x_yocto253_zcu102_debug_opendds3220</url>
    <build_sponsor>Remedy IT</build_sponsor>
    <build_sponsor_url>https://www.remedy.nl</build_sponsor_url>
  </build>
</group>

<group>
  <name>v2.3.1 dev on Linux</name>
  <build>
    <name>rhel80_axcioma231dev_release_ndds610rev3</name>
    <url>https://download.remedy.nl/buildlogs/axcioma/v2.3.1_dev/rhel80_axcioma23x_release_ndds610rev3</url>
    <build_sponsor>Remedy IT</build_sponsor>
    <build_sponsor_url>https://www.remedy.nl</build_sponsor_url>
  </build>
  <build>
    <name>rhel80_axcioma231dev_debug_ndds610rev3</name>
    <url>https://download.remedy.nl/buildlogs/axcioma/v2.3.1_dev/rhel80_axcioma23x_debug_ndds610rev3</url>
    <build_sponsor>Remedy IT</build_sponsor>
    <build_sponsor_url>https://www.remedy.nl</build_sponsor_url>
  </build>
  <build>
    <name>rhel80_axcioma231dev_valgrind_ndds610rev3</name>
    <url>https://download.remedy.nl/buildlogs/axcioma/v2.3.1_dev/rhel80_axcioma23x_valgrind_ndds610rev3</url>
    <build_sponsor>Remedy IT</build_sponsor>
    <build_sponsor_url>https://www.remedy.nl</build_sponsor_url>
  </build>
  <build>
    <name>rhel80_axcioma231dev_yocto253_zcu102_release_ndds610rev3</name>
    <url>https://download.remedy.nl/buildlogs/axcioma/v2.3.1_dev/rhel80_axcioma23x_yocto253_zcu102_release_ndds610rev3</url>
    <build_sponsor>Remedy IT</build_sponsor>
    <build_sponsor_url>https://www.remedy.nl</build_sponsor_url>
  </build>
  <build>
    <name>rhel80_axcioma231dev_yocto253_zcu102_debug_ndds610rev3</name>
    <url>https://download.remedy.nl/buildlogs/axcioma/v2.3.1_dev/rhel80_axcioma23x_yocto253_zcu102_debug_ndds610rev3</url>
    <build_sponsor>Remedy IT</build_sponsor>
    <build_sponsor_url>https://www.remedy.nl</build_sponsor_url>
  </build>
  <build>
    <name>rhel80_axcioma231dev_release_opendds3220</name>
    <url>https://download.remedy.nl/buildlogs/axcioma/v2.3.1_dev/rhel80_axcioma23x_release_opendds3220</url>
    <build_sponsor>Remedy IT</build_sponsor>
    <build_sponsor_url>https://www.remedy.nl</build_sponsor_url>
  </build>
  <build>
    <name>rhel80_axcioma231dev_debug_opendds3220</name>
    <url>https://download.remedy.nl/buildlogs/axcioma/v2.3.1_dev/rhel80_axcioma23x_debug_opendds3220</url>
    <build_sponsor>Remedy IT</build_sponsor>
    <build_sponsor_url>https://www.remedy.nl</build_sponsor_url>
  </build>
  <build>
    <name>rhel80_axcioma231dev_yocto253_zcu102_release_opendds3220</name>
    <url>https://download.remedy.nl/buildlogs/axcioma/v2.3.1_dev/rhel80_axcioma23x_yocto253_zcu102_release_opendds3220</url>
    <build_sponsor>Remedy IT</build_sponsor>
    <build_sponsor_url>https://www.remedy.nl</build_sponsor_url>
  </build>
  <build>
    <name>rhel80_axcioma231dev_yocto253_zcu102_debug_opendds3220</name>
    <url>https://download.remedy.nl/buildlogs/axcioma/v2.3.1_dev/rhel80_axcioma23x_yocto253_zcu102_debug_opendds3220</url>
    <build_sponsor>Remedy IT</build_sponsor>
    <build_sponsor_url>https://www.remedy.nl</build_sponsor_url>
  </build>
</group>

<group>
  <name>v2.4.0 on Linux</name>
  <build>
    <name>rhel80_axcioma240_release_ndds610rev3</name>
    <url>https://download.remedy.nl/buildlogs/axcioma/AXCIOMA_v2.4.0/rhel80_axcioma24x_release_ndds610rev3</url>
    <build_sponsor>Remedy IT</build_sponsor>
    <build_sponsor_url>https://www.remedy.nl</build_sponsor_url>
  </build>
  <build>
    <name>rhel80_axcioma240_debug_ndds610rev3</name>
    <url>https://download.remedy.nl/buildlogs/axcioma/AXCIOMA_v2.4.0/rhel80_axcioma24x_debug_ndds610rev3</url>
    <build_sponsor>Remedy IT</build_sponsor>
    <build_sponsor_url>https://www.remedy.nl</build_sponsor_url>
  </build>
  <build>
    <name>rhel80_axcioma240_valgrind_ndds610rev3</name>
    <url>https://download.remedy.nl/buildlogs/axcioma/AXCIOMA_v2.4.0/rhel80_axcioma24x_valgrind_ndds610rev3</url>
    <build_sponsor>Remedy IT</build_sponsor>
    <build_sponsor_url>https://www.remedy.nl</build_sponsor_url>
  </build>
  <build>
    <name>rhel80_axcioma240_yocto344_zcu102_release_ndds610rev3</name>
    <url>https://download.remedy.nl/buildlogs/axcioma/AXCIOMA_v2.4.0/rhel80_axcioma24x_yocto344_zcu102_release_ndds610rev3</url>
    <build_sponsor>Remedy IT</build_sponsor>
    <build_sponsor_url>https://www.remedy.nl</build_sponsor_url>
  </build>
  <build>
    <name>rhel80_axcioma240_yocto344_zcu102_debug_ndds610rev3</name>
    <url>https://download.remedy.nl/buildlogs/axcioma/AXCIOMA_v2.4.0/rhel80_axcioma24x_yocto344_zcu102_debug_ndds610rev3</url>
    <build_sponsor>Remedy IT</build_sponsor>
    <build_sponsor_url>https://www.remedy.nl</build_sponsor_url>
  </build>
  <build>
    <name>rhel80_axcioma240_release_opendds3241</name>
    <url>https://download.remedy.nl/buildlogs/axcioma/AXCIOMA_v2.4.0/rhel80_axcioma24x_release_opendds3241</url>
    <build_sponsor>Remedy IT</build_sponsor>
    <build_sponsor_url>https://www.remedy.nl</build_sponsor_url>
  </build>
  <build>
    <name>rhel80_axcioma240_debug_opendds3241</name>
    <url>https://download.remedy.nl/buildlogs/axcioma/AXCIOMA_v2.4.0/rhel80_axcioma24x_debug_opendds3241</url>
    <build_sponsor>Remedy IT</build_sponsor>
    <build_sponsor_url>https://www.remedy.nl</build_sponsor_url>
  </build>
  <build>
    <name>rhel80_axcioma240_yocto344_zcu102_release_opendds3241</name>
    <url>https://download.remedy.nl/buildlogs/axcioma/AXCIOMA_v2.4.0/rhel80_axcioma24x_yocto344_zcu102_release_opendds3241</url>
    <build_sponsor>Remedy IT</build_sponsor>
    <build_sponsor_url>https://www.remedy.nl</build_sponsor_url>
  </build>
  <build>
    <name>rhel80_axcioma240_yocto344_zcu102_debug_opendds3241</name>
    <url>https://download.remedy.nl/buildlogs/axcioma/AXCIOMA_v2.4.0/rhel80_axcioma24x_yocto344_zcu102_debug_opendds3241</url>
    <build_sponsor>Remedy IT</build_sponsor>
    <build_sponsor_url>https://www.remedy.nl</build_sponsor_url>
  </build>
</group>

<group>
  <name>v2.4.1 dev on Linux</name>
  <build>
    <name>rhel80_axcioma241dev_release_ndds610rev3</name>
    <url>https://download.remedy.nl/buildlogs/axcioma/v2.4.1_dev/rhel80_axcioma24x_release_ndds610rev3</url>
    <build_sponsor>Remedy IT</build_sponsor>
    <build_sponsor_url>https://www.remedy.nl</build_sponsor_url>
  </build>
  <build>
    <name>rhel80_axcioma241dev_debug_ndds610rev3</name>
    <url>https://download.remedy.nl/buildlogs/axcioma/v2.4.1_dev/rhel80_axcioma24x_debug_ndds610rev3</url>
    <build_sponsor>Remedy IT</build_sponsor>
    <build_sponsor_url>https://www.remedy.nl</build_sponsor_url>
  </build>
  <build>
    <name>rhel80_axcioma241dev_valgrind_ndds610rev3</name>
    <url>https://download.remedy.nl/buildlogs/axcioma/v2.4.1_dev/rhel80_axcioma24x_valgrind_ndds610rev3</url>
    <build_sponsor>Remedy IT</build_sponsor>
    <build_sponsor_url>https://www.remedy.nl</build_sponsor_url>
  </build>
  <build>
    <name>rhel80_axcioma241dev_yocto344_zcu102_release_ndds610rev3</name>
    <url>https://download.remedy.nl/buildlogs/axcioma/v2.4.1_dev/rhel80_axcioma24x_yocto344_zcu102_release_ndds610rev3</url>
    <build_sponsor>Remedy IT</build_sponsor>
    <build_sponsor_url>https://www.remedy.nl</build_sponsor_url>
  </build>
  <build>
    <name>rhel80_axcioma241dev_yocto344_zcu102_debug_ndds610rev3</name>
    <url>https://download.remedy.nl/buildlogs/axcioma/v2.4.1_dev/rhel80_axcioma24x_yocto344_zcu102_debug_ndds610rev3</url>
    <build_sponsor>Remedy IT</build_sponsor>
    <build_sponsor_url>https://www.remedy.nl</build_sponsor_url>
  </build>
  <build>
    <name>rhel80_axcioma241dev_release_opendds3241</name>
    <url>https://download.remedy.nl/buildlogs/axcioma/v2.4.1_dev/rhel80_axcioma24x_release_opendds3241</url>
    <build_sponsor>Remedy IT</build_sponsor>
    <build_sponsor_url>https://www.remedy.nl</build_sponsor_url>
  </build>
  <build>
    <name>rhel80_axcioma241dev_debug_opendds3241</name>
    <url>https://download.remedy.nl/buildlogs/axcioma/v2.4.1_dev/rhel80_axcioma24x_debug_opendds3241</url>
    <build_sponsor>Remedy IT</build_sponsor>
    <build_sponsor_url>https://www.remedy.nl</build_sponsor_url>
  </build>
  <build>
    <name>rhel80_axcioma241dev_yocto344_zcu102_release_opendds3241</name>
    <url>https://download.remedy.nl/buildlogs/axcioma/v2.4.1_dev/rhel80_axcioma24x_yocto344_zcu102_release_opendds3241</url>
    <build_sponsor>Remedy IT</build_sponsor>
    <build_sponsor_url>https://www.remedy.nl</build_sponsor_url>
  </build>
  <build>
    <name>rhel80_axcioma241dev_yocto344_zcu102_debug_opendds3241</name>
    <url>https://download.remedy.nl/buildlogs/axcioma/v2.4.1_dev/rhel80_axcioma24x_yocto344_zcu102_debug_opendds3241</url>
    <build_sponsor>Remedy IT</build_sponsor>
    <build_sponsor_url>https://www.remedy.nl</build_sponsor_url>
  </build>
</group>
</scoreboard>

